LICENSE
MANIFEST.in
README.rst
setup.py
django_webgate.egg-info/PKG-INFO
django_webgate.egg-info/SOURCES.txt
django_webgate.egg-info/dependency_links.txt
django_webgate.egg-info/top_level.txt
webgate/__init__.py
webgate/middleware.py