Metadata-Version: 1.1
Name: django-webgate
Version: 1.0.1
Summary: Django Authentication Middleware for WebGate Oracle AccessManager.
Home-page: https://github.com/boundlessgeo/django-webgate/
Author: Daniel Berry
Author-email: dberry@boundlessgeo.com
License: BSD
Platform: UNKNOWN
Classifier: Environment :: Web Environment
Classifier: Framework :: Django
Classifier: Framework :: Django :: 1.8
Classifier: Intended Audience :: Developers
Classifier: License :: OSI Approved :: MIT License
Classifier: Operating System :: OS Independent
Classifier: Programming Language :: Python
Classifier: Programming Language :: Python :: 2
Classifier: Programming Language :: Python :: 2.7
